signal_desktop_gif/__init__.py
signal_desktop_gif/__main__.py
signal_desktop_gif-0.1.0.dist-info/METADATA
signal_desktop_gif-0.1.0.dist-info/WHEEL
signal_desktop_gif-0.1.0.dist-info/entry_points.txt
signal_desktop_gif-0.1.0.dist-info/licenses/LICENSE
signal_desktop_gif-0.1.0.dist-info/RECORD
