Metadata-Version: 2.3
Name: signal-desktop-gif
Version: 0.1.0
Summary: Paste GIFs into Signal Desktop with a single global keyboard shortcut.
Author-email: Mikuláš Zelinka <mikulas@zelinka.dev>
License-File: LICENSE
Requires-Python: >=3.8
Requires-Dist: httpx>=0.27.0
Requires-Dist: loguru>=0.7.2
Requires-Dist: platformdirs>=4.2.0
Requires-Dist: pyautogui>=0.9.54
Requires-Dist: pynput>=1.7.6
Requires-Dist: pyperclip>=1.8.2
